pyscf-2.12.0.dist-info/WHEEL
pyscf-2.12.0.dist-info/top_level.txt
pyscf-2.12.0.dist-info/METADATA
pyscf-2.12.0.dist-info/RECORD
pyscf-2.12.0.dist-info/licenses/NOTICE
pyscf-2.12.0.dist-info/licenses/LICENSE
pyscf/__config__.py
pyscf/__all__.py
pyscf/post_scf.py
pyscf/__init__.py
pyscf/gto/cmd_args.py
pyscf/gto/pp_int.py
pyscf/gto/ecp.py
pyscf/gto/mole.py
pyscf/gto/ft_ao.py
pyscf/gto/ppnl_velgauge.py
pyscf/gto/moleintor.py
pyscf/gto/eval_gto.py
pyscf/gto/__init__.py
pyscf/gto/basis/DgaussA1_dft_xfit.dat
pyscf/gto/basis/sap_grasp_small.dat
pyscf/gto/basis/dzvp.dat
pyscf/gto/basis/aug-cc-pwcvqz.dat
pyscf/gto/basis/faegre_dz.py
pyscf/gto/basis/bfd_vqz.dat
pyscf/gto/basis/dzp.dat
pyscf/gto/basis/def2-qzvppd-ri.dat
pyscf/gto/basis/cc-pwCVTZ-DK3.dat
pyscf/gto/basis/lanl08.dat
pyscf/gto/basis/aug-pcseg-4.dat
pyscf/gto/basis/demon_cfit.dat
pyscf/gto/basis/def2-tzvp-ri.dat
pyscf/gto/basis/stuttgart_rsc.dat
pyscf/gto/basis/dzp-dkh.dat
pyscf/gto/basis/def2-tzvppd-ri.dat
pyscf/gto/basis/crystal-cc-pvdz.dat
pyscf/gto/basis/sto-6g.dat
pyscf/gto/basis/aug-cc-pvqz.dat
pyscf/gto/basis/cc-pvdpdz.dat
pyscf/gto/basis/cc-pVTZ-DK3.dat
pyscf/gto/basis/aug-cc-pwcvdz.dat
pyscf/gto/basis/cc-pCV6Z.dat
pyscf/gto/basis/aqzp.dat
pyscf/gto/basis/dyall_tz.py
pyscf/gto/basis/cc-pwCV5Z-DK.dat
pyscf/gto/basis/parse_molpro.py
pyscf/gto/basis/def2-qzvpp-ri.dat
pyscf/gto/basis/dzp_dunning.py
pyscf/gto/basis/cc-pvdz-ri.dat
pyscf/gto/basis/aug-cc-pvtz.dat
pyscf/gto/basis/cc-pvtz-ri.dat
pyscf/gto/basis/cc-pwCVTZ-PP.dat
pyscf/gto/basis/cc-pCV5Z.dat
pyscf/gto/basis/ma-def2-svp.dat
pyscf/gto/basis/aug-cc-pv5z-ri.dat
pyscf/gto/basis/def2-qzvp-ri.dat
pyscf/gto/basis/parse_bfd_pp.py
pyscf/gto/basis/dzvp2.dat
pyscf/gto/basis/cc-pVDZ-PP-NR.dat
pyscf/gto/basis/def2-universal-jfit.dat
pyscf/gto/basis/cc-pvqz.dat
pyscf/gto/basis/cc-pwCV5Z-PP.dat
pyscf/gto/basis/tzv.dat
pyscf/gto/basis/sarc-dkh2.dat
pyscf/gto/basis/cc-pVTZ-PP-NR.dat
pyscf/gto/basis/weigend_cfit.dat
pyscf/gto/basis/bfd_vdz.dat
pyscf/gto/basis/cc-pwCV5Z.dat
pyscf/gto/basis/cc-pwCVTZ-DK.dat
pyscf/gto/basis/cc-pvdz_fit.dat
pyscf/gto/basis/bfd_pp.dat
pyscf/gto/basis/def2-tzvpp.dat
