Metadata-Version: 2.4
Name: pyscf
Version: 2.12.0
Summary: PySCF: Python-based Simulations of Chemistry Framework
Author-email: Qiming Sun <osirpt.sun@gmail.com>
Maintainer-email: Qiming Sun <osirpt.sun@gmail.com>
License: Apache-2.0
Project-URL: Homepage, http://www.pyscf.org
Project-URL: Repository, https://github.com/pyscf/pyscf
Project-URL: Documentation, http://www.pyscf.org
Classifier: Development Status :: 5 - Production/Stable
Classifier: Intended Audience :: Science/Research
Classifier: Intended Audience :: Developers
Classifier: License :: OSI Approved :: Apache Software License
Classifier: Programming Language :: C
Classifier: Programming Language :: Python
Classifier: Programming Language :: Python :: 3.7
Classifier: Programming Language :: Python :: 3.8
Classifier: Programming Language :: Python :: 3.9
Classifier: Programming Language :: Python :: 3.10
Classifier: Programming Language :: Python :: 3.11
Classifier: Programming Language :: Python :: 3.12
Classifier: Topic :: Software Development
Classifier: Topic :: Scientific/Engineering
Classifier: Operating System :: POSIX
Classifier: Operating System :: Unix
Classifier: Operating System :: MacOS
License-File: LICENSE
License-File: NOTICE
Requires-Dist: numpy!=1.16,!=1.17,>=1.13
Requires-Dist: scipy>=1.6.0
Requires-Dist: h5py>=2.7
Requires-Dist: setuptools
Provides-Extra: forge
Requires-Dist: pyscf-forge; extra == "forge"
Provides-Extra: geomopt
Requires-Dist: pyberny>=0.6.2; extra == "geomopt"
Requires-Dist: geometric>=0.9.7.2; extra == "geomopt"
Requires-Dist: pyscf-qsdopt; extra == "geomopt"
Provides-Extra: doci
Requires-Dist: pyscf-doci; extra == "doci"
Provides-Extra: properties
Requires-Dist: pyscf-properties; extra == "properties"
Provides-Extra: semiempirical
Requires-Dist: pyscf-semiempirical; extra == "semiempirical"
Provides-Extra: cppe
Requires-Dist: cppe; extra == "cppe"
Provides-Extra: pyqmc
Requires-Dist: pyqmc; extra == "pyqmc"
Provides-Extra: bse
Requires-Dist: basis-set-exchange; extra == "bse"
Provides-Extra: dispersion
Requires-Dist: pyscf-dispersion; extra == "dispersion"
Provides-Extra: ccpy
Requires-Dist: coupled-cluster-py; extra == "ccpy"
Provides-Extra: all
Requires-Dist: pyscf[bse,ccpy,cppe,dispersion,doci,forge,geomopt,properties,pyqmc,semiempirical]; extra == "all"
Provides-Extra: cornell-shci
Requires-Dist: pyscf-cornell-shci; extra == "cornell-shci"
Provides-Extra: nao
Requires-Dist: pyscf-nao; extra == "nao"
Provides-Extra: fciqmcscf
Requires-Dist: pyscf-fciqmc; extra == "fciqmcscf"
Provides-Extra: tblis
Requires-Dist: pyscf-tblis; extra == "tblis"
Provides-Extra: icmpspt
Requires-Dist: pyscf-icmpspt; extra == "icmpspt"
Provides-Extra: shciscf
Requires-Dist: pyscf-shciscf; extra == "shciscf"
Dynamic: license-file
